otomodachi/__init__.py
otomodachi/__main__.py
otomodachi/nexauth.py
otomodachi/nexplc.py
otomodachi/proxy.py
otomodachi-0.0.1.dist-info/WHEEL
otomodachi-0.0.1.dist-info/METADATA
otomodachi-0.0.1.dist-info/RECORD
