Metadata-Version: 2.1
Name: otomodachi
Version: 0.0.1
Summary: Omron PLC Connectivity Library
Author-email: Filip Svoboda <filip.svoboda@gmail.com>
Requires-Python: >=3.7
Classifier: Programming Language :: Python :: 3
Classifier: License :: OSI Approved :: GNU Lesser General Public License v3 (LGPLv3)
Classifier: Operating System :: OS Independent
Requires-Dist: cryptography
Requires-Dist: hexdump
Requires-Dist: requests
Project-URL: Bug Tracker, https://github.com/FilipSvoboda/otomodachi/issues
Project-URL: Homepage, https://github.com/FilipSvoboda/otomodachi
